{
    "questions": [
      {"num1": 52, "num2": 12, "num3": 20, "answer": 84},
      {"num1": 32, "num2": 12, "num3": 22, "answer": 66},
      {"num1": 55, "num2": 23, "num3": 12, "answer": 90},
      {"num1": 52, "num2": 33, "num3": -20, "answer": 65},
      {"num1": 14, "num2": 23, "num3": 21, "answer": 58},
      {"num1": 70, "num2": 12, "num3": 25, "answer": 107},
      {"num1": 32, "num2": 52, "num3": -25, "answer": 59},
      {"num1": 14, "num2": 50, "num3": -33, "answer": 31},
      {"num1": 26, "num2": 32, "num3": 14, "answer": 72},
      {"num1": 52, "num2": 32, "num3": -52, "answer": 32},
      {"num1": 147, "num2": 258, "num3": -321, "answer": 84},
      {"num1": 452, "num2": 325, "num3": 633, "answer": 1410},
      {"num1": 654, "num2": 232, "num3": -300, "answer": 586},
      {"num1": 145, "num2": 255, "num3": 322, "answer": 722},
      {"num1": 658, "num2": 236, "num3": -522, "answer": 372},
      {"num1": 458, "num2": 325, "num3": -652, "answer": 131},
      {"num1": 256, "num2": 321, "num3": 145, "answer": 722},
      {"num1": 258, "num2": 321, "num3": -222, "answer": 357},
      {"num1": 258, "num2": 321, "num3": 144, "answer": 723},
      {"num1": 441, "num2": 222, "num3": 321, "answer": 984},
      {
        "num1": 111,
        "num2": 222,
        "num3": 555,
        "answer": 888
      },
      {
        "num1": 222,
        "num2": 555,
        "num3": -666,
        "answer": 111
      },
      {
        "num1": 444,
        "num2": 111,
        "num3": 222,
        "answer": 777
      },
      {
        "num1": 333,
        "num2": 222,
        "num3": 111,
        "answer": 666
      },
      {
        "num1": 666,
        "num2": 444,
        "num3": 222,
        "answer": 1332
      },
      {
        "num1": 222,
        "num2": 333,
        "num3": 555,
        "answer": 1110
      },
      {
        "num1": 222,
        "num2": 444,
        "num3": -222,
        "answer": 444
      },
      {
        "num1": 333,
        "num2": 222,
        "num3": 555,
        "answer": 1110
      },
      {
        "num1": 666,
        "num2": 333,
        "num3": -777,
        "answer": 222
      },
      {
        "num1": 222,
        "num2": 888,
        "num3": -555,
        "answer": 555
      }
    ]
  }
